randomnum/__init__.py
randomnum/gentor.py
randomyy-1.0.0.dist-info/METADATA
randomyy-1.0.0.dist-info/WHEEL
randomyy-1.0.0.dist-info/top_level.txt
randomyy-1.0.0.dist-info/RECORD
