Metadata-Version: 2.1
Name: randomyy
Version: 1.0.0
Summary: Library for generating random numbers
Home-page: UNKNOWN
Author: Your Name
Author-email: UNKNOWN
License: UNKNOWN
Platform: UNKNOWN
